tests/__init__.py
tests/cooperative_test.py
tests/esusu_test.py
tests/group_test.py
tests/individual_test.py
tests/main_test.py
tests/xauto_test.py
tests/xvault_test.py
xend_finance/__init__.py
xend_finance/main.py
xend_finance/test.py
xend_finance/environment/__init__.py
xend_finance/environment/testnet.py
xend_finance/models/__init__.py
xend_finance/models/schemas.py
xend_finance/strategies/__init__.py
xend_finance/strategies/contract.py
xend_finance/strategies/abis/ClientRecord.json
xend_finance/strategies/abis/Cycles.json
xend_finance/strategies/abis/DaiContract.json
xend_finance/strategies/abis/DaiLendingService.json
xend_finance/strategies/abis/ER20.json
xend_finance/strategies/abis/EsusuAdapter.json
xend_finance/strategies/abis/EsusuService.json
xend_finance/strategies/abis/EsusuStorage.json
xend_finance/strategies/abis/FortubeAdapterTestnet.json
xend_finance/strategies/abis/Groups.json
xend_finance/strategies/abis/ProtocolAdapter.json
xend_finance/strategies/abis/XendFinanceGroup.json
xend_finance/strategies/abis/XendFinanceIndividual_Yearn_V1.json
xend_finance/strategies/abis/XendToken.json
xend_finance/strategies/abis/__init__.py
xend_finance/strategies/abis/busd.json
xend_finance/strategies/abis/esusu-service.json
xend_finance/strategies/abis/file_handler.py
xend_finance/strategies/abis/groups.json
xend_finance/strategies/abis/index.py
xend_finance/strategies/abis/xAuto.json
xend_finance/strategies/abis/xVault.json
xend_finance/strategies/abis/V2XAuto/ApyPoolBSCV2.json
xend_finance/strategies/abis/V2XAuto/xvAutoBNBV2.json
xend_finance/strategies/abis/V2XAuto/xvAutoBUSDV2.json
xend_finance/strategies/abis/V2XAuto/xvAutoUSDCV2.json
xend_finance/strategies/abis/V2XAuto/xvAutoUSDTV2.json
xend_finance/strategies/abis/V2XAutoMatic/APYPoolMaticV2.json
xend_finance/strategies/abis/V2XAutoMatic/xvAutoAAVEV2.json
xend_finance/strategies/abis/V2XAutoMatic/xvAutoUSDCV2.json
xend_finance/strategies/abis/V2XAutoMatic/xvAutoUSDTV2.json
xend_python_sdk-0.1.8.dist-info/LICENSE
xend_python_sdk-0.1.8.dist-info/METADATA
xend_python_sdk-0.1.8.dist-info/WHEEL
xend_python_sdk-0.1.8.dist-info/top_level.txt
xend_python_sdk-0.1.8.dist-info/RECORD
