Metadata-Version: 2.1
Name: xend-python-sdk
Version: 0.1.8
Summary: The Xend Finance SDK arms python developers with the ability to build DeFi     applications with Xend Finance without needing to understand the complexities      of the underlying blockchain or layer2 infrastructure.
Home-page: https://github.com/E-wave112/xend-python
Author: Osagie Iyayi
Author-email: iyayiemmanuel1@gmail.com
License: MIT
Keywords: python,blockchain,cryptocurrency,layer2,defi
Classifier: Development Status :: 5 - Production/Stable
Classifier: Intended Audience :: Developers
Classifier: Topic :: Software Development :: Build Tools
Classifier: License :: OSI Approved :: MIT License
Classifier: Programming Language :: Python :: 3
Classifier: Programming Language :: Python :: 3.7
Classifier: Programming Language :: Python :: 3.8
Classifier: Programming Language :: Python :: 3.9
Classifier: Programming Language :: Python :: 3.10
Classifier: Topic :: Software Development :: Libraries
License-File: LICENSE
Requires-Dist: web3
Requires-Dist: web3[tester]
Requires-Dist: requests
